{"Version":"0.0.0","Data":{"GameSetup":"{\"_settings\":[{\"Name\":\"Mode\",\"SettingType\":3,\"Version\":0,\"BoolValue\":false,\"IntValue\":0,\"FloatValue\":0.0,\"StringValue\":\"Custom\",\"Protected\":false,\"FloatArrayValue\":[],\"IsSet\":false},{\"Name\":\"UID\",\"SettingType\":3,\"Version\":0,\"BoolValue\":false,\"IntValue\":0,\"FloatValue\":0.0,\"StringValue\":\"e6261428b6d349d79a507e492b2e8482\",\"Protected\":false,\"FloatArrayValue\":[],\"IsSet\":false},{\"Name\":\"GameSetting.Vail.EnemyHealth\",\"SettingType\":3,\"Version\":0,\"BoolValue\":false,\"IntValue\":0,\"FloatValue\":0.0,\"StringValue\":\"LOW\",\"Protected\":false,\"FloatArrayValue\":[],\"IsSet\":false},{\"Name\":\"GameSetting.Vail.EnemyDamage\",\"SettingType\":3,\"Version\":0,\"BoolValue\":false,\"IntValue\":0,\"FloatValue\":0.0,\"StringValue\":\"LOW\",\"Protected\":false,\"FloatArrayValue\":[],\"IsSet\":false},{\"Name\":\"GameSetting.Vail.EnemyAggression\",\"SettingType\":3,\"Version\":0,\"BoolValue\":false,\"IntValue\":0,\"FloatValue\":0.0,\"StringValue\":\"LOW\",\"Protected\":false,\"FloatArrayValue\":[],\"IsSet\":false},{\"Name\":\"GameSetting.Environment.SeasonLength\",\"SettingType\":3,\"Version\":0,\"BoolValue\":false,\"IntValue\":0,\"FloatValue\":0.0,\"StringValue\":\"Default\",\"Protected\":false,\"FloatArrayValue\":[],\"IsSet\":false},{\"Name\":\"GameSetting.Environment.DayLength\",\"SettingType\":3,\"Version\":0,\"BoolValue\":false,\"IntValue\":0,\"FloatValue\":0.0,\"StringValue\":\"Long\",\"Protected\":false,\"FloatArrayValue\":[],\"IsSet\":false},{\"Name\":\"GameSetting.Environment.PrecipitationFrequency\",\"SettingType\":3,\"Version\":0,\"BoolValue\":false,\"IntValue\":0,\"FloatValue\":0.0,\"StringValue\":\"Default\",\"Protected\":false,\"FloatArrayValue\":[],\"IsSet\":false},{\"Name\":\"GameSetting.Survival.ConsumableEffects\",\"SettingType\":3,\"Version\":0,\"BoolValue\":false,\"IntValue\":0,\"FloatValue\":0.0,\"StringValue\":\"Normal\",\"Protected\":false,\"FloatArrayValue\":[],\"IsSet\":false}],\"name\":\"\",\"hideFlags\":0}"}}